pydtac/__init__.py
pydtac/host/__init__.py
pydtac/host/default_host.py
pydtac/host/plugin_host.py
pydtac/host/plugin_pb2.py
pydtac/host/plugin_pb2_grpc.py
pydtac/host/helpers/__init__.py
pydtac/host/helpers/debug_sender.py
pydtac/host/helpers/encryptor.py
pydtac/host/helpers/network.py
pydtac/plugins/__init__.py
pydtac/plugins/base.py
pydtac/plugins/types.py
pydtac/plugins/validation.py
pydtac-0.9.4.dist-info/METADATA
pydtac-0.9.4.dist-info/WHEEL
pydtac-0.9.4.dist-info/top_level.txt
pydtac-0.9.4.dist-info/RECORD
